<?xml version="1.0" encoding="Windows-1252"?>
<CharacterSetting xmlns:xsi="http://www.w3.org/2001/XMLSchema-instance" xmlns:xsd="http://www.w3.org/2001/XMLSchema">
  <Id>11</Id>
  <UserPlayerId>22</UserPlayerId>
  <CharacterId>1</CharacterId>
  <Name>Silor dady</Name>
  <Level>5</Level>
  <Updated>true</Updated>
  <LastUpdated>2019-01-25T09:42:28.0055061-06:00</LastUpdated>
  <IsEnable>true</IsEnable>
  <FightMode>false</FightMode>
  <Alive>true</Alive>
  <Life>1</Life>
  <Coin>8816</Coin>
  <Gem>1419</Gem>
  <Experience>5209</Experience>
  <MaxExperience>6500</MaxExperience>
  <HandsCnt>2</HandsCnt>
  <MaxHealth>700</MaxHealth>
  <Health>700</Health>
  <MaxMana>350</MaxMana>
  <Mana>350</Mana>
  <MaxEnergy>1400</MaxEnergy>
  <Energy>1400</Energy>
  <SpeedAttack>10</SpeedAttack>
  <SpeedDefense>5</SpeedDefense>
  <AbilityAttack>50</AbilityAttack>
  <AbilityDefense>0</AbilityDefense>
  <MagicAttack>2</MagicAttack>
  <MagicDefense>4</MagicDefense>
  <PoisonAttack>0</PoisonAttack>
  <PoisonDefense>0</PoisonDefense>
  <Element>None</Element>
  <Carry>24</Carry>
  <CarryCnt>7</CarryCnt>
  <Speed>5</Speed>
  <Intellect>0</Intellect>
  <Agility>0</Agility>
  <Strength>0</Strength>
  <Stamina>0</Stamina>
  <Crafting>1</Crafting>
  <Researching>0</Researching>
  <Bravery>0</Bravery>
  <Charming>0</Charming>
  <Equipments>
    <ItemContainer />
    <ItemContainer />
    <ItemContainer />
    <ItemContainer />
    <ItemContainer />
    <ItemContainer />
    <ItemContainer />
    <ItemContainer />
    <ItemContainer />
    <ItemContainer />
    <ItemContainer>
      <Equipment>
        <Id>5</Id>
        <Name>Basic Glove</Name>
        <Description>Basic glove from animal leather</Description>
        <IconPath>Inventory/InventorySet1</IconPath>
        <IconId>204</IconId>
        <Cost>3</Cost>
        <Weight>1</Weight>
        <MaxStackCnt>2</MaxStackCnt>
        <StackCnt>2</StackCnt>
        <Type>Equipment</Type>
        <Rarity>Common</Rarity>
        <IsUnique>false</IsUnique>
        <Slug>BasicGlove</Slug>
        <DurationDays>365</DurationDays>
        <ExpirationTime>2019-06-28T18:35:01.5138436-05:00</ExpirationTime>
        <IsEnable>true</IsEnable>
        <PlaceHolder>Feet</PlaceHolder>
        <Agility>0</Agility>
        <Bravery>0</Bravery>
        <Carry>0</Carry>
        <CarryCnt>0</CarryCnt>
        <Charming>0</Charming>
        <Intellect>0</Intellect>
        <Crafting>1</Crafting>
        <Researching>0</Researching>
        <Speed>0</Speed>
        <Stamina>0</Stamina>
        <Strength>0</Strength>
      </Equipment>
    </ItemContainer>
    <ItemContainer>
      <Weapon>
        <Id>2</Id>
        <Name>Small Sword</Name>
        <Description>Small Sword</Description>
        <IconPath>Inventory/InventorySet1</IconPath>
        <IconId>73</IconId>
        <Cost>10</Cost>
        <Weight>3</Weight>
        <MaxStackCnt>1</MaxStackCnt>
        <StackCnt>1</StackCnt>
        <Type>Weapon</Type>
        <Rarity>Common</Rarity>
        <IsUnique>true</IsUnique>
        <Slug>SmallSword</Slug>
        <DurationDays>365</DurationDays>
        <ExpirationTime>2019-06-14T15:17:24.2938024-05:00</ExpirationTime>
        <IsEnable>true</IsEnable>
        <CarryType>OneHand</CarryType>
        <SpeedAttack>1</SpeedAttack>
        <SpeedDefense>0</SpeedDefense>
        <AbilityAttack>10</AbilityAttack>
        <AbilityDefense>0</AbilityDefense>
        <MagicAttack>0</MagicAttack>
        <MagicDefense>0</MagicDefense>
        <PoisonAttack>0</PoisonAttack>
        <PoisonDefense>0</PoisonDefense>
      </Weapon>
    </ItemContainer>
    <ItemContainer>
      <Tool>
        <Id>6</Id>
        <Name>Iron Shovel</Name>
        <Description>Iron Shovel</Description>
        <IconPath>Inventory/InventoryTools</IconPath>
        <IconId>16</IconId>
        <Cost>10</Cost>
        <Weight>5</Weight>
        <MaxStackCnt>1</MaxStackCnt>
        <StackCnt>1</StackCnt>
        <Type>Tool</Type>
        <Rarity>Common</Rarity>
        <IsUnique>true</IsUnique>
        <Slug>IronShovel</Slug>
        <DurationDays>365</DurationDays>
        <ExpirationTime>2019-08-09T11:51:45.0731418-05:00</ExpirationTime>
        <IsEnable>true</IsEnable>
        <TimeToUse>928</TimeToUse>
        <FavouriteElement>Hole</FavouriteElement>
      </Tool>
    </ItemContainer>
    <ItemContainer />
  </Equipments>
</CharacterSetting>